tradingeconomics/__init__.py
tradingeconomics/calendar.py
tradingeconomics/comtrade.py
tradingeconomics/credit_ratings.py
tradingeconomics/dividends.py
tradingeconomics/earnings.py
tradingeconomics/eurostat.py
tradingeconomics/federalReserve.py
tradingeconomics/financials.py
tradingeconomics/forecasts.py
tradingeconomics/functions.py
tradingeconomics/glob.py
tradingeconomics/historical.py
tradingeconomics/historicalDB.py
tradingeconomics/historicalEurostat.py
tradingeconomics/historicalFinancials.py
tradingeconomics/historicalMarkets.py
tradingeconomics/indicators.py
tradingeconomics/ipo.py
tradingeconomics/markets.py
tradingeconomics/news.py
tradingeconomics/search.py
tradingeconomics/stock_splits.py
tradingeconomics/stream.py
tradingeconomics/worldBank.py
tradingeconomics-4.5.8.dist-info/licenses/LICENSE
tradingeconomics-4.5.8.dist-info/METADATA
tradingeconomics-4.5.8.dist-info/WHEEL
tradingeconomics-4.5.8.dist-info/top_level.txt
tradingeconomics-4.5.8.dist-info/RECORD
