Metadata-Version: 2.4
Name: tradingeconomics
Version: 4.5.8
Summary: Trading Economics API
Home-page: https://github.com/tradingeconomics/tradingeconomics-python
Download-URL: https://github.com/tradingeconomics/tradingeconomics-python/tree/main/dist
Author: Trading Economics
Author-email: support@tradingeconomics.com
License: MIT
Keywords: tradingeconomics,data
Classifier: Programming Language :: Python :: 3
Classifier: Programming Language :: Python :: 3.2
Classifier: Programming Language :: Python :: 3.3
Classifier: Programming Language :: Python :: 3.4
Classifier: Programming Language :: Python :: 3.8
License-File: LICENSE
Requires-Dist: pandas
Requires-Dist: websocket-client
Dynamic: author
Dynamic: author-email
Dynamic: classifier
Dynamic: description
Dynamic: description-content-type
Dynamic: download-url
Dynamic: home-page
Dynamic: keywords
Dynamic: license
Dynamic: license-file
Dynamic: requires-dist
Dynamic: summary
